README.md
setup.py
kcw/Events.py
kcw/__init__.py
kcw/app.py
kcw/kcw.py
kcw.egg-info/PKG-INFO
kcw.egg-info/SOURCES.txt
kcw.egg-info/dependency_links.txt
kcw.egg-info/entry_points.txt
kcw.egg-info/requires.txt
kcw.egg-info/top_level.txt
kcw/common/__init__.py
kcw/common/autoload.py
kcw/common/globals.py
kcw/common/request.py
kcw/config/__init__.py
kcw/common/__init__.py
kcw/common/autoload.py
kcw/common/globals.py
kcw/common/request.py
kcw/config/__init__.py